[{"file_name": "backend/frames/s1e1/frame0.jpg", "color": [4, 4, 4], "timestamp": "0:00:00"}, {"file_name": "backend/frames/s1e1/frame1439.jpg", "color": [31, 27, 33], "timestamp": "0:01:00"}, {"file_name": "backend/frames/s1e1/frame2878.jpg", "color": [108, 143, 174], "timestamp": "0:02:00"}, {"file_name": "backend/frames/s1e1/frame4317.jpg", "color": [28, 40, 53], "timestamp": "0:03:00"}, {"file_name": "backend/frames/s1e1/frame5756.jpg", "color": [132, 154, 170], "timestamp": "0:04:00"}, {"file_name": "backend/frames/s1e1/frame7195.jpg", "color": [113, 130, 151], "timestamp": "0:05:00"}, {"file_name": "backend/frames/s1e1/frame8634.jpg", "color": [9, 13, 21], "timestamp": "0:06:00"}, {"file_name": "backend/frames/s1e1/frame10073.jpg", "color": [10, 13, 19], "timestamp": "0:07:00"}, {"file_name": "backend/frames/s1e1/frame11512.jpg", "color": [57, 39, 30], "timestamp": "0:08:00"}, {"file_name": "backend/frames/s1e1/frame12951.jpg", "color": [179, 205, 217], "timestamp": "0:09:00"}, {"file_name": "backend/frames/s1e1/frame14390.jpg", "color": [47, 48, 55], "timestamp": "0:10:00"}, {"file_name": "backend/frames/s1e1/frame15829.jpg", "color": [45, 45, 48], "timestamp": "0:11:00"}, {"file_name": "backend/frames/s1e1/frame17268.jpg", "color": [16, 13, 15], "timestamp": "0:12:00"}, {"file_name": "backend/frames/s1e1/frame18707.jpg", "color": [25, 26, 31], "timestamp": "0:13:00"}, {"file_name": "backend/frames/s1e1/frame20146.jpg", "color": [69, 82, 75], "timestamp": "0:14:00"}, {"file_name": "backend/frames/s1e1/frame21585.jpg", "color": [38, 45, 48], "timestamp": "0:15:00"}, {"file_name": "backend/frames/s1e1/frame23024.jpg", "color": [32, 34, 42], "timestamp": "0:16:00"}, {"file_name": "backend/frames/s1e1/frame24463.jpg", "color": [28, 34, 42], "timestamp": "0:17:00"}, {"file_name": "backend/frames/s1e1/frame25902.jpg", "color": [35, 41, 49], "timestamp": "0:18:00"}, {"file_name": "backend/frames/s1e1/frame27341.jpg", "color": [38, 27, 21], "timestamp": "0:19:00"}, {"file_name": "backend/frames/s1e1/frame28780.jpg", "color": [39, 31, 26], "timestamp": "0:20:00"}, {"file_name": "backend/frames/s1e1/frame30219.jpg", "color": [33, 34, 36], "timestamp": "0:21:00"}, {"file_name": "backend/frames/s1e1/frame31658.jpg", "color": [39, 39, 38], "timestamp": "0:22:00"}, {"file_name": "backend/frames/s1e1/frame33097.jpg", "color": [20, 17, 19], "timestamp": "0:23:00"}, {"file_name": "backend/frames/s1e1/frame34536.jpg", "color": [30, 30, 34], "timestamp": "0:24:00"}, {"file_name": "backend/frames/s1e1/frame35975.jpg", "color": [46, 52, 60], "timestamp": "0:25:00"}, {"file_name": "backend/frames/s1e1/frame37414.jpg", "color": [48, 51, 56], "timestamp": "0:26:00"}, {"file_name": "backend/frames/s1e1/frame38853.jpg", "color": [27, 31, 37], "timestamp": "0:27:00"}, {"file_name": "backend/frames/s1e1/frame40292.jpg", "color": [40, 39, 46], "timestamp": "0:28:00"}, {"file_name": "backend/frames/s1e1/frame41731.jpg", "color": [12, 9, 10], "timestamp": "0:29:00"}, {"file_name": "backend/frames/s1e1/frame43170.jpg", "color": [9, 8, 9], "timestamp": "0:30:00"}, {"file_name": "backend/frames/s1e1/frame44609.jpg", "color": [32, 28, 27], "timestamp": "0:31:00"}, {"file_name": "backend/frames/s1e1/frame46048.jpg", "color": [35, 33, 34], "timestamp": "0:32:00"}, {"file_name": "backend/frames/s1e1/frame47487.jpg", "color": [20, 13, 10], "timestamp": "0:33:00"}, {"file_name": "backend/frames/s1e1/frame48926.jpg", "color": [41, 29, 22], "timestamp": "0:34:00"}, {"file_name": "backend/frames/s1e1/frame50365.jpg", "color": [65, 45, 32], "timestamp": "0:35:00"}, {"file_name": "backend/frames/s1e1/frame51804.jpg", "color": [74, 51, 39], "timestamp": "0:36:00"}, {"file_name": "backend/frames/s1e1/frame53243.jpg", "color": [123, 85, 72], "timestamp": "0:37:00"}, {"file_name": "backend/frames/s1e1/frame54682.jpg", "color": [63, 51, 33], "timestamp": "0:38:00"}, {"file_name": "backend/frames/s1e1/frame56121.jpg", "color": [61, 52, 43], "timestamp": "0:39:00"}, {"file_name": "backend/frames/s1e1/frame57560.jpg", "color": [31, 26, 24], "timestamp": "0:40:00"}, {"file_name": "backend/frames/s1e1/frame58999.jpg", "color": [10, 8, 10], "timestamp": "0:41:00"}, {"file_name": "backend/frames/s1e1/frame60438.jpg", "color": [12, 10, 12], "timestamp": "0:42:00"}, {"file_name": "backend/frames/s1e1/frame61877.jpg", "color": [13, 11, 13], "timestamp": "0:43:00"}, {"file_name": "backend/frames/s1e1/frame63316.jpg", "color": [17, 12, 11], "timestamp": "0:44:00"}, {"file_name": "backend/frames/s1e1/frame64755.jpg", "color": [30, 20, 14], "timestamp": "0:45:00"}, {"file_name": "backend/frames/s1e1/frame66194.jpg", "color": [25, 15, 10], "timestamp": "0:46:00"}, {"file_name": "backend/frames/s1e1/frame67633.jpg", "color": [17, 17, 17], "timestamp": "0:47:00"}, {"file_name": "backend/frames/s1e1/frame69072.jpg", "color": [19, 19, 21], "timestamp": "0:48:00"}, {"file_name": "backend/frames/s1e1/frame70511.jpg", "color": [18, 15, 15], "timestamp": "0:49:00"}, {"file_name": "backend/frames/s1e1/frame71950.jpg", "color": [178, 166, 166], "timestamp": "0:50:00"}, {"file_name": "backend/frames/s1e1/frame73389.jpg", "color": [64, 54, 49], "timestamp": "0:51:00"}, {"file_name": "backend/frames/s1e1/frame74828.jpg", "color": [73, 53, 42], "timestamp": "0:52:00"}, {"file_name": "backend/frames/s1e1/frame76267.jpg", "color": [51, 33, 25], "timestamp": "0:53:00"}, {"file_name": "backend/frames/s1e1/frame77706.jpg", "color": [229, 222, 225], "timestamp": "0:54:00"}, {"file_name": "backend/frames/s1e1/frame79145.jpg", "color": [68, 52, 44], "timestamp": "0:55:00"}, {"file_name": "backend/frames/s1e1/frame80584.jpg", "color": [183, 117, 91], "timestamp": "0:56:00"}, {"file_name": "backend/frames/s1e1/frame82023.jpg", "color": [235, 162, 122], "timestamp": "0:57:01"}, {"file_name": "backend/frames/s1e1/frame83462.jpg", "color": [31, 33, 41], "timestamp": "0:58:01"}, {"file_name": "backend/frames/s1e1/frame84901.jpg", "color": [44, 52, 44], "timestamp": "0:59:01"}, {"file_name": "backend/frames/s1e1/frame86340.jpg", "color": [22, 21, 20], "timestamp": "1:00:01"}, {"file_name": "backend/frames/s1e1/frame87779.jpg", "color": [4, 4, 4], "timestamp": "1:01:01"}]